whitebox_plugin_map_icons/pyproject.toml
whitebox_plugin_map_icons/__init__.py
whitebox_plugin_map_icons/jsx/SetMapIconServiceComponent.jsx
whitebox_plugin_map_icons/static/whitebox_plugin_map_icons/assets/plane.svg
whitebox_plugin_map_icons/whitebox_plugin_map_icons.py
whitebox_test_plugin_map_icons/__init__.py
whitebox_test_plugin_map_icons/test_whitebox_plugin_map_icons.py
whitebox_plugin_map_icons-0.1.6.dist-info/LICENSE
whitebox_plugin_map_icons-0.1.6.dist-info/METADATA
whitebox_plugin_map_icons-0.1.6.dist-info/WHEEL
whitebox_plugin_map_icons-0.1.6.dist-info/RECORD
